rwssl/__init__.py
rwssl/__main__.py
rwssl/rwssl.py
rwssl/tools.py
rwssl/utils.py
rwssl/templates/acme.tpl
rwssl/templates/nginx-main.tpl
rwssl/templates/nginx-ssl.tpl
rwssl/templates/nginx-sslforced.tpl
rwssl/templates/nginx.tpl
rwssl-2.0.4.dist-info/METADATA
rwssl-2.0.4.dist-info/WHEEL
rwssl-2.0.4.dist-info/entry_points.txt
rwssl-2.0.4.dist-info/top_level.txt
rwssl-2.0.4.dist-info/RECORD
